{
	"core:mountain" : {
		"types" : {
			"hotaHighlandMountains" : {
				"name" : "Mountain",
				"templates" : {
					"AVLMHS00" : { "animation" : "mountains/AVLMHS00", 
					"mask" : [ "VVVVVV","VVBBBB","VBBBBB","VBBBVV" ], 		
                    "allowedTerrains": [ "highlands" ]
					},						
					
					"AVLMHS01" : { "animation" : "mountains/AVLMHS01", 
					"mask" : [ "VVVVVV","VBBBBV","VBBBBB","VVVBBB" ], 
                    "allowedTerrains": [ "highlands" ]
					},
					
					"AVLMHS02" : { "animation" : "mountains/AVLMHS02", 
					"mask" : [ "VVVVV","VBBBV","VBBVV" ], 
                    "allowedTerrains": [ "highlands" ]
					},
					
					"AVLMHS03" : { "animation" : "mountains/AVLMHS03", 
					"mask" : [ "VVVVV", "VBBBV","VVBBV" ], 
                    "allowedTerrains": [ "highlands" ]
					},
					
					"AVLMHS04" : { "animation" : "mountains/AVLMHS04", 
					"mask" : [ "VVVVV", "VVBBV","VBBVV" ], 
                    "allowedTerrains": [ "highlands" ]
					},
					
					"AVLMHS05" : { "animation" : "mountains/AVLMHS05", 
					"mask" : [ "VVVVV", "VBBVV","VVBBV" ], 
                    "allowedTerrains": [ "highlands" ]
					}			
				}
			},
			
			"hotaWastelandMountains" : {
				"name" : "Mountain",
				"templates" : {
					"AVLMtWL1" : { "animation" : "mountains/AVLMtWL1", 
					"mask" : [ "VVVVVV","VBBBBV","VBBBBB","VVVBBB" ], 		
                    "allowedTerrains": [ "wasteland" ]
					},						
					
					"AVLMtWL2" : { "animation" : "mountains/AVLMtWL2", 
					"mask" : [ "VVVVVV","VVBBBB","VBBBBB","VBBBVV" ], 
                    "allowedTerrains": [ "wasteland" ]
					},
					
					"AVLMtWL3" : { "animation" : "mountains/AVLMtWL3", 
					"mask" : [ "VVVV","VBBB","VVBB" ], 
                    "allowedTerrains": [ "wasteland" ]
					},
					
					"AVLMtWL4" : { "animation" : "mountains/AVLMtWL4", 
					"mask" : [ "VVVV", "VBBB","VBBV" ], 
                    "allowedTerrains": [ "wasteland" ]
					},
					
					"AVLMtWL5" : { "animation" : "mountains/AVLMtWL5", 
					"mask" : [ "VVVV", "VBBV","VVBB" ], 
                    "allowedTerrains": [ "wasteland" ]
					},
					
					"AVLMtWL6" : { "animation" : "mountains/AVLMtWL6", 
					"mask" : [ "VVVV", "VVBB","VBBV" ], 
                    "allowedTerrains": [ "wasteland" ]
					},
					
					"AVLMtWL7" : { "animation" : "mountains/AVLMtWL7", 
					"mask" : [ "VVVV", "VVVV","VBVB" ], 
                    "allowedTerrains": [ "wasteland" ]
					}
				}
			}
		}	
	}	
}
	
	


	